Metadata-Version: 1.1
Name: simple-salesforce-wrapper
Version: 0.2.0
Summary: Simple Salesforce is a basic Salesforce.com REST API client. The goal is to provide a very low-level interface to the API, returning an ordered dictionary of the API JSON response.
Home-page: https://github.com/afrobeard/simple-salesforce-wrapper
Author: Iqbal Talaat
Author-email: iqbaltalaat@gmail.com
License: Apache 2.0
Keywords: python salesforce salesforce.com
Platform: UNKNOWN
Classifier: Development Status :: 4 - Beta
Classifier: License :: OSI Approved :: Apache Software License
Classifier: Intended Audience :: Developers
Classifier: Intended Audience :: System Administrators
Classifier: Operating System :: OS Independent
Classifier: Topic :: Internet :: WWW/HTTP
Classifier: Programming Language :: Python :: 2.6
Classifier: Programming Language :: Python :: 2.7
Classifier: Programming Language :: Python :: 3.3
Classifier: Programming Language :: Python :: 3.4
Classifier: Programming Language :: Python :: Implementation :: PyPy
